tricots.py
tricots-0.1.0.dist-info/LICENSE
tricots-0.1.0.dist-info/METADATA
tricots-0.1.0.dist-info/WHEEL
tricots-0.1.0.dist-info/RECORD
