Metadata-Version: 2.1
Name: tricots
Version: 0.1.0
Summary: Trace Interception and Collection Tool
License: MIT
Author: Diego Dorn
Requires-Python: >=3.9,<4.0
Classifier: License :: OSI Approved :: MIT License
Classifier: Programming Language :: Python :: 3
Classifier: Programming Language :: Python :: 3.9
Classifier: Programming Language :: Python :: 3.10
Classifier: Programming Language :: Python :: 3.11
Classifier: Programming Language :: Python :: 3.12
Requires-Dist: openai
